redshift_data_api/__init__.py
redshift_data_api-1.2.5.dist-info/METADATA
redshift_data_api-1.2.5.dist-info/WHEEL
redshift_data_api-1.2.5.dist-info/RECORD
